datapoints/__init__.py
datapoints/channel.py
datapoints/channel_opcua_client.py
datapoints/channel_virtual.py
datapoints/datapoint.py
datapoints/signal.py
datapoints/utils/__init__.py
datapoints/utils/logger.py
datapoints-0.0.2.dist-info/WHEEL
datapoints-0.0.2.dist-info/METADATA
datapoints-0.0.2.dist-info/RECORD
