Metadata-Version: 2.1
Name: datapoints
Version: 0.0.2
Summary: Управление данными
Home-page: https://github.com/Konstantin-Dudersky/data_connector
Author: Konstantin-Dudersky
Author-email: Konstantin.Dudersky@gmail.com
Requires-Python: >=3.10.0,<3.11.0
Classifier: Programming Language :: Python :: 3
Classifier: Programming Language :: Python :: 3.10
Requires-Dist: asyncua (==0.9.94)
Project-URL: Repository, https://github.com/Konstantin-Dudersky/data_connector
